gif.py
gif-23.3.0.dist-info/LICENSE
gif-23.3.0.dist-info/METADATA
gif-23.3.0.dist-info/WHEEL
gif-23.3.0.dist-info/top_level.txt
gif-23.3.0.dist-info/RECORD
