Metadata-Version: 2.1
Name: gif
Version: 23.3.0
Summary: The matplotlib Animation Extension
Home-page: https://github.com/maxhumber/gif
Author: Max Humber
Author-email: max.humber@gmail.com
License: MIT
Keywords: gif,gifs,animation,PIL,pillow,matplotlib
Classifier: Development Status :: 5 - Production/Stable
Classifier: Topic :: Multimedia :: Graphics
Requires-Python: >=3.9
Provides-Extra: dev
Provides-Extra: test
License-File: LICENSE
